PT3S/Am.py
PT3S/Dm.py
PT3S/Dx.py
PT3S/Lx.py
PT3S/Mx.py
PT3S/NFD.py
PT3S/Rm.py
PT3S/Xm.py
PT3S/__init__.py
PT3S/conf.py
PT3S/dxAndMxHelperFcts.py
PT3S/dxDecodeObjsData.py
PT3S/ncd.py
PT3S/pNFD.py
PT3S/sdfCsv.py
PT3S/Examples/Example1.db3
PT3S/Examples/Example2.db3
PT3S/Examples/Example3.db3
PT3S/Examples/Example5.db3
PT3S/Examples/Example6.db3
PT3S/Examples/Example7.db3
PT3S/Examples/Example8.db3
PT3S/Examples/Example9_1.db3
PT3S/Examples/Example9_2.db3
PT3S/Examples/Example9_3.db3
PT3S/Examples/WDExample1/B1/V0/BZ1/M-1-0-1.1.MX1
PT3S/Examples/WDExample1/B1/V0/BZ1/M-1-0-1.MX2
PT3S/Examples/WDExample1/B1/V0/BZ1/M-1-0-1.XML
PT3S/Examples/WDExample2/B1/V0/BZ1/M-1-0-1.5.MX1
PT3S/Examples/WDExample2/B1/V0/BZ1/M-1-0-1.MX2
PT3S/Examples/WDExample2/B1/V0/BZ1/M-1-0-1.XML
PT3S/Examples/WDExample3/B1/V0/BZ1/M-1-0-1.1.MX1
PT3S/Examples/WDExample3/B1/V0/BZ1/M-1-0-1.MX2
PT3S/Examples/WDExample3/B1/V0/BZ1/M-1-0-1.XML
PT3S/Examples/WDExample5/B1/V0/BZ1/M-1-0-1.1.MX1
PT3S/Examples/WDExample5/B1/V0/BZ1/M-1-0-1.MX2
PT3S/Examples/WDExample5/B1/V0/BZ1/M-1-0-1.XML
PT3S/Examples/WDExample6/B1/V0/BZ1/M-1-0-1.1.MX1
PT3S/Examples/WDExample6/B1/V0/BZ1/M-1-0-1.MX2
PT3S/Examples/WDExample6/B1/V0/BZ1/M-1-0-1.XML
PT3S/Examples/WDExample7/B1/V0/BZ1/M-1-0-1.1.MX1
PT3S/Examples/WDExample7/B1/V0/BZ1/M-1-0-1.MX2
PT3S/Examples/WDExample7/B1/V0/BZ1/M-1-0-1.XML
PT3S/Examples/WDExample7_2/B1/V0/BZ1/M-1-0-1.1.MX1
PT3S/Examples/WDExample7_2/B1/V0/BZ1/M-1-0-1.MX2
PT3S/Examples/WDExample7_2/B1/V0/BZ1/M-1-0-1.XML
PT3S/Examples/WDExample8/B1/V0/BZ1/M-1-0-1.1.MX1
PT3S/Examples/WDExample8/B1/V0/BZ1/M-1-0-1.MX2
PT3S/Examples/WDExample8/B1/V0/BZ1/M-1-0-1.XML
PT3S/Examples/WDExample9_2/B1/V0/BZ1/M-1-0-1.1.MX1
PT3S/Examples/WDExample9_2/B1/V0/BZ1/M-1-0-1.MX2
PT3S/Examples/WDExample9_2/B1/V0/BZ1/M-1-0-1.XML
PT3S/Examples/WDExample9_3/B1/V0/BZ1/M-1-0-1.1.MX1
PT3S/Examples/WDExample9_3/B1/V0/BZ1/M-1-0-1.MX2
PT3S/Examples/WDExample9_3/B1/V0/BZ1/M-1-0-1.XML
UTILS/Db.py
UTILS/Xml.py
UTILS/__init__.py
lds/__init__.py
pt3s-90.15.1.dist-info/licenses/LICENSE
pt3s-90.15.1.dist-info/METADATA
pt3s-90.15.1.dist-info/WHEEL
pt3s-90.15.1.dist-info/top_level.txt
pt3s-90.15.1.dist-info/RECORD
