Metadata-Version: 2.4
Name: PT3S
Version: 90.15.1
Summary: Python Tools 3S
Author-email: 3S Consult GmbH <jablonski@3sconsult.de>
License-Expression: MIT
Project-URL: Documentation, https://3sconsult.github.io/PT3S
Project-URL: Source, https://github.com/3SConsult/PT3S
Keywords: Python,3S,SIR 3S,SIR Graf,SIR Calc,3S Consult
Requires-Python: >=3
License-File: LICENSE
Requires-Dist: tables
Requires-Dist: pandas
Requires-Dist: numpy
Requires-Dist: h5py
Requires-Dist: pyodbc
Requires-Dist: geopandas
Requires-Dist: networkx
Requires-Dist: shapely
Requires-Dist: contextily
Requires-Dist: py7zr
Requires-Dist: folium
Requires-Dist: mapclassify
Requires-Dist: sqlalchemy
Requires-Dist: matplotlib
Dynamic: license-file
